.gitignore
publishpack.sh
setup.py
pdbwebtemplate/__init__.py
pdbwebtemplate.egg-info/PKG-INFO
pdbwebtemplate.egg-info/SOURCES.txt
pdbwebtemplate.egg-info/dependency_links.txt
pdbwebtemplate.egg-info/top_level.txt
pdbwebtemplate.egg-info/zip-safe
pdbwebtemplate/core/__init__.py
pdbwebtemplate/core/configfile.py
pdbwebtemplate/core/connection.py
pdbwebtemplate/core/coreclassesweb.py
pdbwebtemplate/core/exceptions.py
pdbwebtemplate/core/externalauth.py
pdbwebtemplate/core/my_jinja.py
pdbwebtemplate/core/routepages.py
pdbwebtemplate/core/api/__init__.py
pdbwebtemplate/core/api/contact.py
pdbwebtemplate/core/api/forgotpassword.py
pdbwebtemplate/core/api/login.py
pdbwebtemplate/core/api/loginbase.py
pdbwebtemplate/core/api/loginsocial.py
pdbwebtemplate/core/api/password.py
pdbwebtemplate/core/api/registeruser.py
pdbwebtemplate/core/api/updatemail.py
pdbwebtemplate/core/api/updateuser.py
pdbwebtemplate/core/business/__init__.py
pdbwebtemplate/core/business/baserequestpromo.py
pdbwebtemplate/core/business/consultpromo.py
pdbwebtemplate/core/business/contact.py
pdbwebtemplate/core/business/extractpromo.py
pdbwebtemplate/core/business/forgotpassword.py
pdbwebtemplate/core/business/login.py
pdbwebtemplate/core/business/participationpromo.py
pdbwebtemplate/core/business/password.py
pdbwebtemplate/core/business/sendemail.py
pdbwebtemplate/core/business/user.py
pdbwebtemplate/core/business/util.py
pdbwebtemplate/core/models/__init__.py
pdbwebtemplate/core/models/storemailcontact.py
pdbwebtemplate/core/models/userndb.py
pdbwebtemplate/core/models/usertoken.py
pdbwebtemplate/core/spi/__init__.py
pdbwebtemplate/core/spi/consultpromo.py
pdbwebtemplate/core/spi/participationpromo.py
pdbwebtemplate/mypromo/settings.ini
pdbwebtemplate/mypromo/auth_json/pdbcontest_auth.json
pdbwebtemplate/mypromo/auth_json/pdbcontesttest1_auth.json