Metadata-Version: 1.0
Name: pdbwebtemplate
Version: 0.3.4
Summary: Template Model for web projects
Home-page: https://Ferraresi@gitlab.com/promodebolso/pdbwebtemplate.git
Author: Richard Ferraresi
Author-email: richard@promodebolso.com.br
License: Comercial
Platform: UNKNOWN
